{"show": "Million Dollars, But...", "slug": "million-dollars-but", "summary": {"count": 53, "uploaded": 53, "missing": 0, "incomplete": 0, "removed": 0}, "data": [{"title": "Animated Holiday Special", "id": "29557", "slug": "million-dollars-but-season-5-animated-holiday-special", "date": "2018-11-28", "is_first": false, "is_uploaded": true, "is_complete_upload": true, "is_removed": false}, {"title": "Claws and Effect", "id": "26051", "slug": "million-dollars-but-season-5-claws-and-effect", "date": "2018-03-22", "is_first": false, "is_uploaded": true, "is_complete_upload": true, "is_removed": false}, {"title": "Puppet Pandemonium", "id": "25984", "slug": "million-dollars-but-season-5-puppet-pandemonium", "date": "2018-03-15", "is_first": false, "is_uploaded": true, "is_complete_upload": true, "is_removed": false}, {"title": "Chrono Oh No!", "id": "24641", "slug": "million-dollars-but-season-5-gct", "date": "2018-03-08", "is_first": false, "is_uploaded": true, "is_complete_upload": true, "is_removed": false}, {"title": "Barbara's Explosion of Emotion", "id": "24519", "slug": "million-dollars-but-season-5-barbara-s-explosion-of-emotion", "date": "2018-03-01", "is_first": false, "is_uploaded": true, "is_complete_upload": true, "is_removed": false}, {"title": "A Million Pounds, Although", "id": "24443", "slug": "million-dollars-but-season-5-a-million-pounds-although", "date": "2018-02-22", "is_first": false, "is_uploaded": true, "is_complete_upload": true, "is_removed": false}, {"title": "Sugar Pine 7 Can't Poop", "id": "23939", "slug": "million-dollars-but-season-5-sugar-pine-7-can-t-poop", "date": "2018-02-15", "is_first": false, "is_uploaded": true, "is_complete_upload": true, "is_removed": false}, {"title": "Funhaus All Lubed Up", "id": "23919", "slug": "million-dollars-but-season-5-2", "date": "2018-02-08", "is_first": false, "is_uploaded": true, "is_complete_upload": true, "is_removed": false}, {"title": "Achievement Hunter Sandal Scandal", "id": "23915", "slug": "million-dollars-but-season-5-1", "date": "2018-02-01", "is_first": false, "is_uploaded": true, "is_complete_upload": true, "is_removed": false}, {"title": "Dungeons, Dragons, and Dumbasses", "id": "23653", "slug": "million-dollars-but-theme-pack-dungeons-dragons-and-dumbasses", "date": "2018-01-18", "is_first": false, "is_uploaded": true, "is_complete_upload": true, "is_removed": false}, {"title": "Holiday: 12 Crimes of Christmas", "id": "9132", "slug": "million-dollars-but-theme-pack-holiday", "date": "2017-12-14", "is_first": false, "is_uploaded": true, "is_complete_upload": true, "is_removed": false}, {"title": "Pok\u00e9-Pandemonium & Ashley the Furry", "id": "9133", "slug": "million-dollars-but-theme-pack-poke-pandemonium-ashley-the-furry", "date": "2017-12-07", "is_first": false, "is_uploaded": true, "is_complete_upload": true, "is_removed": false}, {"title": "Femme Fatales", "id": "9134", "slug": "million-dollars-but-theme-pack-femme-fatales", "date": "2017-11-30", "is_first": false, "is_uploaded": true, "is_complete_upload": true, "is_removed": false}, {"title": "Anime Fights & Tantalizing Tentacles", "id": "9135", "slug": "million-dollars-but-theme-pack-anime-fights-tantalizing-tentacles", "date": "2017-11-23", "is_first": false, "is_uploaded": true, "is_complete_upload": true, "is_removed": false}, {"title": "Hannah Hart in: Historic Hauntings", "id": "9136", "slug": "million-dollars-but-season-4-8-sfi7yj", "date": "2017-05-23", "is_first": false, "is_uploaded": true, "is_complete_upload": true, "is_removed": false}, {"title": "Phil DeFranco in Screaming Food", "id": "9137", "slug": "million-dollars-but-season-4-7-jg9yukg", "date": "2017-05-16", "is_first": false, "is_uploaded": true, "is_complete_upload": true, "is_removed": false}, {"title": "80's Flashback", "id": "9139", "slug": "million-dollars-but-season-4-5-j9ugkf", "date": "2017-05-02", "is_first": false, "is_uploaded": true, "is_complete_upload": true, "is_removed": false}, {"title": "All You Can Eat - ft. Grace Helbig", "id": "9140", "slug": "million-dollars-but-season-4-4-ah8gh4k", "date": "2017-04-25", "is_first": false, "is_uploaded": true, "is_complete_upload": true, "is_removed": false}, {"title": "Tweeting for Trump", "id": "9141", "slug": "million-dollars-but-season-4-3-98-gh3o", "date": "2017-04-18", "is_first": false, "is_uploaded": true, "is_complete_upload": true, "is_removed": false}, {"title": "Wayward Wiener", "id": "9142", "slug": "million-dollars-but-season-4-2-sjghiru", "date": "2017-04-11", "is_first": false, "is_uploaded": true, "is_complete_upload": true, "is_removed": false}, {"title": "Founding Fathers", "id": "9143", "slug": "million-dollars-but-season-4-founding-fathers", "date": "2017-04-04", "is_first": false, "is_uploaded": true, "is_complete_upload": true, "is_removed": false}, {"title": "Season 4 - Trailer", "id": "84-bonus", "slug": "million-dollars-but-bonus-1", "date": "2017-03-28", "is_first": false, "is_uploaded": true, "is_complete_upload": true, "is_removed": false}, {"title": "Super Bloopers!", "id": "9144", "slug": "million-dollars-but-season-3-super-bloopers", "date": "2016-09-28", "is_first": true, "is_uploaded": true, "is_complete_upload": true, "is_removed": false}, {"title": "Screaming Penis", "id": "9146", "slug": "million-dollars-but-season-3-screaming-penis", "date": "2016-09-21", "is_first": false, "is_uploaded": true, "is_complete_upload": true, "is_removed": false}, {"title": "The Jerk Off Text", "id": "9145", "slug": "million-dollars-but-season-3-the-jerk-off-text", "date": "2016-09-14", "is_first": false, "is_uploaded": true, "is_complete_upload": true, "is_removed": false}, {"title": "Old People Punching", "id": "9147", "slug": "million-dollars-but-season-3-old-people-punching", "date": "2016-09-07", "is_first": false, "is_uploaded": true, "is_complete_upload": true, "is_removed": false}, {"title": "Burnie Bloopers & Barbara Burps", "id": "9148", "slug": "million-dollars-but-season-3-burnie-bloopers-barbara-burps", "date": "2016-08-31", "is_first": true, "is_uploaded": true, "is_complete_upload": true, "is_removed": false}, {"title": "Girls vs Ninjas", "id": "9149", "slug": "million-dollars-but-season-3-girls-vs-ninjas", "date": "2016-08-24", "is_first": false, "is_uploaded": true, "is_complete_upload": true, "is_removed": false}, {"title": "Slow Mo Millionaires", "id": "9150", "slug": "million-dollars-but-season-3-slow-mo-millionaires", "date": "2016-08-17", "is_first": false, "is_uploaded": true, "is_complete_upload": true, "is_removed": false}, {"title": "Hunted by Linebackers", "id": "9151", "slug": "million-dollars-but-season-3-hunted-by-linebackers", "date": "2016-08-10", "is_first": false, "is_uploaded": true, "is_complete_upload": true, "is_removed": false}, {"title": "Million Dollars, But\u2026 Season 3 \u2013 Official Trailer", "id": "9152", "slug": "million-dollars-but-season-3-season-3-trailer", "date": "2016-08-03", "is_first": false, "is_uploaded": true, "is_complete_upload": true, "is_removed": false}, {"title": "How to Play Million Dollars, But... The Game", "id": "9153", "slug": "million-dollars-but-season-2-how-to-play-million-dollars-but-the-game", "date": "2016-06-08", "is_first": false, "is_uploaded": true, "is_complete_upload": true, "is_removed": false}, {"title": "Million Dollars, But... The Game Announcement", "id": "9156", "slug": "million-dollars-but-season-2-million-dollars-but-the-game-announcement", "date": "2016-05-11", "is_first": false, "is_uploaded": true, "is_complete_upload": true, "is_removed": false}, {"title": "Extinguishing Butt Fires \u2013 Million Dollars, But Bloopers", "id": "9155", "slug": "million-dollars-but-season-2-extinguishing-butt-fires-million-dollars-but-bloopers", "date": "2016-03-30", "is_first": false, "is_uploaded": true, "is_complete_upload": true, "is_removed": false}, {"title": "Flaming Butts \u2013 MILLION DOLLARS, BUT... Season Finale", "id": "9154", "slug": "million-dollars-but-season-2-flaming-butts-million-d-o-l-l-a-r-s-b-u-t-season-finale", "date": "2016-03-23", "is_first": false, "is_uploaded": true, "is_complete_upload": true, "is_removed": false}, {"title": "Achievement Hunter Animal Attack", "id": "9157", "slug": "million-dollars-but-season-2-achievement-hunter-animal-attack", "date": "2016-03-16", "is_first": false, "is_uploaded": true, "is_complete_upload": true, "is_removed": false}, {"title": "Evil Twin & Fart Parade", "id": "9158", "slug": "million-dollars-but-season-2-evil-twin-fart-parade", "date": "2016-03-09", "is_first": false, "is_uploaded": true, "is_complete_upload": true, "is_removed": false}, {"title": "Million Dollars, But... Bloopers & Outtakes #3", "id": "9159", "slug": "million-dollars-but-season-2-bloopers-outtakes", "date": "2016-03-02", "is_first": false, "is_uploaded": true, "is_complete_upload": true, "is_removed": false}, {"title": "Biggest Belieber & Knife-hand", "id": "9160", "slug": "million-dollars-but-season-2-biggest-belieber-and-knife-hand", "date": "2016-02-24", "is_first": false, "is_uploaded": true, "is_complete_upload": true, "is_removed": false}, {"title": "Puppet Arms & Giant Womb", "id": "9161", "slug": "million-dollars-but-season-2-2", "date": "2016-02-17", "is_first": false, "is_uploaded": true, "is_complete_upload": true, "is_removed": false}, {"title": "Mime Time & Serial Hugger", "id": "9162", "slug": "million-dollars-but-season-2-mime-time-serial-hugger", "date": "2016-02-11", "is_first": false, "is_uploaded": true, "is_complete_upload": true, "is_removed": false}, {"title": "Million Dollars, But\u2026 Season 2 - Official Trailer", "id": "9163", "slug": "million-dollars-but-season-2-million-dollars-but-season-2-official-trailer", "date": "2016-02-10", "is_first": false, "is_uploaded": true, "is_complete_upload": true, "is_removed": false}, {"title": "Tongue Hands & Leaky Nips", "id": "9164", "slug": "million-dollars-but-season-1-temp", "date": "2015-12-20", "is_first": false, "is_uploaded": true, "is_complete_upload": true, "is_removed": false}, {"title": "Bleed Out & Sneeze Teleport", "id": "9165", "slug": "million-dollars-but-season-1-bleed-out-sneeze-teleport", "date": "2015-09-09", "is_first": false, "is_uploaded": true, "is_complete_upload": true, "is_removed": false}, {"title": "Million Dollars, But... Bloopers & Outtakes #2", "id": "9166", "slug": "million-dollars-but-season-1-1", "date": "2015-09-02", "is_first": false, "is_uploaded": true, "is_complete_upload": true, "is_removed": false}, {"title": "Sudden Nudity & Permanent Parachutes", "id": "9167", "slug": "million-dollars-but-season-1-sudden-nudity-permanent-parachutes", "date": "2015-08-26", "is_first": false, "is_uploaded": true, "is_complete_upload": true, "is_removed": false}, {"title": "Baby Burnie & Hitler Honeymoon", "id": "9168", "slug": "million-dollars-but-season-1-baby-burnie-hitler-honeymoon", "date": "2015-08-19", "is_first": false, "is_uploaded": true, "is_complete_upload": true, "is_removed": false}, {"title": "Magic Dogs & Muscle Men", "id": "9169", "slug": "million-dollars-but-season-1-magic-dogs-and-muscle-men", "date": "2015-08-05", "is_first": false, "is_uploaded": true, "is_complete_upload": true, "is_removed": false}, {"title": "Million Dollars, But... Bloopers & Outtakes", "id": "9170", "slug": "million-dollars-but-season-1-million-dollars-but-bloopers-outtakes", "date": "2015-07-29", "is_first": false, "is_uploaded": true, "is_complete_upload": true, "is_removed": false}, {"title": "Birthday Sex & Negativity Light", "id": "9171", "slug": "million-dollars-but-season-1-episode-3", "date": "2015-07-22", "is_first": false, "is_uploaded": true, "is_complete_upload": true, "is_removed": false}, {"title": "Money Mouth & Delayed Climax", "id": "9172", "slug": "million-dollars-but-season-1-money-mouth-and-delayed-climax", "date": "2015-07-15", "is_first": false, "is_uploaded": true, "is_complete_upload": true, "is_removed": false}, {"title": "Glowing Dicks & Pretty Chicks", "id": "26182", "slug": "million-dollars-but-season-1-glowing-dicks-and-pretty-chicks", "date": "2015-07-08", "is_first": false, "is_uploaded": true, "is_complete_upload": true, "is_removed": false}, {"title": "Million Dollars, But...", "id": "9174", "slug": "million-dollars-but-season-1-million-dollars-but", "date": "2015-05-20", "is_first": false, "is_uploaded": true, "is_complete_upload": true, "is_removed": false}]}