{"show": "The Dogbark Podcast", "slug": "the-dogbark-podcast", "summary": {"count": 26, "uploaded": 26, "missing": 0, "incomplete": 0, "removed": 0}, "data": [{"title": "S2:E26 - Talkin' About Late Nights with Joe", "id": "52748", "slug": "the-dogbark-podcast-season-2-dbp26", "date": "2024-03-28", "is_first": true, "is_uploaded": true, "is_complete_upload": true, "is_removed": false}, {"title": "S2:E25 - Talkin' About Apex Legends", "id": "52713", "slug": "the-dogbark-podcast-season-2-s2-e25-talkin-about-apex-legends", "date": "2024-03-20", "is_first": true, "is_uploaded": true, "is_complete_upload": true, "is_removed": false}, {"title": "S2:E24 -  Talkin' About Rooster Teeth Ending", "id": "52684", "slug": "the-dogbark-podcast-season-2-talkin-about-rooster-teeth-ending", "date": "2024-03-13", "is_first": true, "is_uploaded": true, "is_complete_upload": true, "is_removed": false}, {"title": "S2:E23 - Talkin' About Dune: Part 2", "id": "52660", "slug": "the-dogbark-podcast-season-2-s2-e23-talkin-about-dune-part-2", "date": "2024-03-06", "is_first": true, "is_uploaded": true, "is_complete_upload": true, "is_removed": false}, {"title": "S2:E22 - Talkin' About The ULTIMATE Onewheel", "id": "52616", "slug": "the-dogbark-podcast-season-2-talkin-about-the-ultimate-onewheel", "date": "2024-02-28", "is_first": true, "is_uploaded": true, "is_complete_upload": true, "is_removed": false}, {"title": "S2:E21 - Talkin' About Oscar-Worthy Madame Web", "id": "52576", "slug": "the-dogbark-podcast-season-2-talkin-about-oscar-worthy-madame-web", "date": "2024-02-21", "is_first": true, "is_uploaded": true, "is_complete_upload": true, "is_removed": false}, {"title": "S2:E20 - Talkin' About Our Mosh Pit Roles", "id": "52537", "slug": "the-dogbark-podcast-season-2-talkin-about-our-mosh-pit-roles", "date": "2024-02-14", "is_first": true, "is_uploaded": true, "is_complete_upload": true, "is_removed": false}, {"title": "S2:E19 - Talkin' About Joe's Google Results", "id": "52496", "slug": "the-dogbark-podcast-season-1-michael-gets-a-one-wheel", "date": "2024-02-07", "is_first": true, "is_uploaded": true, "is_complete_upload": true, "is_removed": false}, {"title": "S2:E18 - Talkin' About Food Poisoning & CUMcore", "id": "52452", "slug": "the-dogbark-podcast-season-1-talkin-about-food-poisoning-cumcore", "date": "2024-01-31", "is_first": true, "is_uploaded": true, "is_complete_upload": true, "is_removed": false}, {"title": "S2:E17 - Talkin' About Concerts & Tonal", "id": "52411", "slug": "the-dogbark-podcast-season-1-talkin-about-concerts-tonal", "date": "2024-01-24", "is_first": true, "is_uploaded": true, "is_complete_upload": true, "is_removed": false}, {"title": "S2:E16 - Talkin' About Doing Our Nails", "id": "52365", "slug": "the-dogbark-podcast-season-1-s1-e16-talkin-about-doing-our-nails", "date": "2024-01-17", "is_first": true, "is_uploaded": true, "is_complete_upload": true, "is_removed": false}, {"title": "S2:E15 - Talkin' About What We Did During the Holidays!", "id": "52338", "slug": "the-dogbark-podcast-season-1-talkin-about-what-we-did-during-the-holidays", "date": "2024-01-10", "is_first": true, "is_uploaded": true, "is_complete_upload": true, "is_removed": false}, {"title": "S2:E14 - Talkin' About Backflips & More Godzilla", "id": "52307", "slug": "the-dogbark-podcast-season-1-talkin-about-backflips-more-godzilla", "date": "2024-01-03", "is_first": true, "is_uploaded": true, "is_complete_upload": true, "is_removed": false}, {"title": "S1:E13 - Talkin' About The Finals & Godzilla", "id": "52243", "slug": "the-dogbark-podcast-season-1-talkin-about-the-finals-godzilla", "date": "2023-12-27", "is_first": true, "is_uploaded": true, "is_complete_upload": true, "is_removed": false}, {"title": "S1:E12 - Talkin' About 2023 Game Awards & 7 Days to Die", "id": "52241", "slug": "the-dogbark-podcast-season-1-talkin-about-2023-game-awards-7-days-to-die", "date": "2023-12-20", "is_first": true, "is_uploaded": true, "is_complete_upload": true, "is_removed": false}, {"title": "S1:E11 - Talkin' About Working Out & Hanging Out", "id": "52204", "slug": "the-dogbark-podcast-season-1-talkin-about-working-out-hanging-out", "date": "2023-12-13", "is_first": true, "is_uploaded": true, "is_complete_upload": true, "is_removed": false}, {"title": "S1:E10 - Talkin' About Engagements & Snoring", "id": "52162", "slug": "the-dogbark-podcast-season-1-talkin-about-engagements-snoring", "date": "2023-12-06", "is_first": true, "is_uploaded": true, "is_complete_upload": true, "is_removed": false}, {"title": "S1:E9 - Talkin' About Thanksgiving and Movies", "id": "52111", "slug": "the-dogbark-podcast-season-1-talkin-about-thanksgiving-and-movies", "date": "2023-11-29", "is_first": true, "is_uploaded": true, "is_complete_upload": true, "is_removed": false}, {"title": "S1:E8 - Talkin' About Movies and Mega Man", "id": "52065", "slug": "the-dogbark-podcast-season-1-talkin-about-movies-and-mega-man", "date": "2023-11-22", "is_first": true, "is_uploaded": true, "is_complete_upload": true, "is_removed": false}, {"title": "S1:E7 - Talkin' About Getting Hot & Thicc", "id": "51996", "slug": "the-dogbark-podcast-season-1-the-seventh-one-ever", "date": "2023-11-15", "is_first": true, "is_uploaded": true, "is_complete_upload": true, "is_removed": false}, {"title": "S1:E6 - Talkin' About BTS", "id": "51943", "slug": "the-dogbark-podcast-season-1-the-sixth-one-ever", "date": "2023-11-08", "is_first": true, "is_uploaded": true, "is_complete_upload": true, "is_removed": false}, {"title": "S1:E5 - Talkin' About Halloween", "id": "51888", "slug": "the-dogbark-podcast-season-1-the-fifth-one-ever", "date": "2023-11-01", "is_first": true, "is_uploaded": true, "is_complete_upload": true, "is_removed": false}, {"title": "S1:E4 - Talkin' About TV Shows", "id": "51838", "slug": "the-dogbark-podcast-season-1-the-fourth-one-ever", "date": "2023-10-25", "is_first": true, "is_uploaded": true, "is_complete_upload": true, "is_removed": false}, {"title": "S1:E3 - Talkin' About Chicken Horse", "id": "51783", "slug": "the-dogbark-podcast-season-1-the-third-one-ever", "date": "2023-10-18", "is_first": true, "is_uploaded": true, "is_complete_upload": true, "is_removed": false}, {"title": "S1:E2 - Talkin' About Beaches", "id": "51727", "slug": "the-dogbark-podcast-season-1-the-second-one-ever", "date": "2023-10-11", "is_first": true, "is_uploaded": true, "is_complete_upload": true, "is_removed": false}, {"title": "S1:E1 - Talkin' About The Dogbark Podcast", "id": "51680", "slug": "the-dogbark-podcast-season-1-first-one-ever", "date": "2023-10-04", "is_first": false, "is_uploaded": true, "is_complete_upload": true, "is_removed": false}]}