{
    "show": "Know Your Thrones",
    "slug": "know-your-thrones",
    "summary": {
        "count": 7,
        "uploaded": 7,
        "missing": 0,
        "incomplete": 0,
        "removed": 0
    },
    "data": [
        {
            "title": "TOO MUCH OF A GOOD THING? - KNOW YOUR THRONES, the Game of Thrones Nerdalong for Season 7 Episode 7",
            "id": "897",
            "slug": "know-your-thrones-game-of-thrones-season-7-too-much-of-a-good-t-h-i-n-g-know-your-t-h-r-o-n-e-s-the-game-of-thrones-nerdalong-for-season-7-episode-7",
            "date": "2017-09-03",
            "is_first": false,
            "is_uploaded": true,
            "is_complete_upload": true,
            "is_removed": false
        },
        {
            "title": "THE MAGNIFICENT SEVEN - KNOW YOUR THRONES, the Game of Thrones Nerdalong for Season 7 Episode 6",
            "id": "899",
            "slug": "know-your-thrones-game-of-thrones-season-7-the-magnificent-seven-know-your-t-h-r-o-n-e-s-the-game-of-thrones-nerdalong-for-season-7-episode-6",
            "date": "2017-08-23",
            "is_first": false,
            "is_uploaded": true,
            "is_complete_upload": true,
            "is_removed": false
        },
        {
            "title": "JON SNOW IS WHAT? - KNOW YOUR THRONES, the Game of Thrones Nerdalong for Season 7 Episode 5",
            "id": "900",
            "slug": "know-your-thrones-game-of-thrones-season-7-jon-snow-is-w-h-a-t-know-your-t-h-r-o-n-e-s-game-of-thrones-season-7-episode-5-nerdathon",
            "date": "2017-08-15",
            "is_first": false,
            "is_uploaded": true,
            "is_complete_upload": true,
            "is_removed": false
        },
        {
            "title": "The Big Payoff - KNOW YOUR THRONES, the Game of Thrones Nerdalong for Season 7 Episode 4",
            "id": "901",
            "slug": "know-your-thrones-game-of-thrones-season-7-4",
            "date": "2017-08-09",
            "is_first": false,
            "is_uploaded": true,
            "is_complete_upload": true,
            "is_removed": false
        },
        {
            "title": "Daenerys Has Too Many Titles - KNOW YOUR THRONES, the Game of Thrones Nerdalong for Season 7 Episode 3",
            "id": "902",
            "slug": "know-your-thrones-game-of-thrones-season-7-3",
            "date": "2017-08-01",
            "is_first": false,
            "is_uploaded": true,
            "is_complete_upload": true,
            "is_removed": false
        },
        {
            "title": "Euron Trouble Now - KNOW YOUR THRONES, the Game of Thrones Nerdalong for Season 7 Episode 2",
            "id": "903",
            "slug": "know-your-thrones-game-of-thrones-season-7-2",
            "date": "2017-07-25",
            "is_first": false,
            "is_uploaded": true,
            "is_complete_upload": true,
            "is_removed": false
        },
        {
            "title": "WINTER IS HERE - KNOW YOUR THRONES, the Game of Thrones Nerdalong for Season 7 Episode 1",
            "id": "904",
            "slug": "know-your-thrones-game-of-thrones-season-7",
            "date": "2017-07-18",
            "is_first": false,
            "is_uploaded": true,
            "is_complete_upload": true,
            "is_removed": false
        }
    ]
}